fastdev/__init__.py
fastdev/__main__.py
fastdev/config.py
fastdev/fs_serving.py
fastdev/router.py
fastdev/ts_serving.py
fastdev/utils.py
fastdev/deno_ltbs/deps.ts
fastdev/deno_ltbs/esbuild_builder.ts
fastdev/deno_ltbs/html_builder.ts
fastdev/deno_ltbs/mod.ts
fastdev/preprocessor/temp.py.bak
fastdev_py-0.5.0.dist-info/entry_points.txt
fastdev_py-0.5.0.dist-info/WHEEL
fastdev_py-0.5.0.dist-info/METADATA
fastdev_py-0.5.0.dist-info/RECORD
