Metadata-Version: 2.1
Name: fastdev-py
Version: 0.5.0
Summary: FastAPI development server that JIT preprocess TS, TSX, SCSS, etc... files.
Keywords: devserver,dev-server,devtools,sever,liveserver,live-server
Author: Omar Azmi
Requires-Python: >=3.11
Requires-Dist: fastapi
Project-URL: Homepage, https://github.com/omar-azmi/fastdev_py
Project-URL: Source, https://github.com/omar-azmi/fastdev_py
